textual_dominfo/__init__.py
textual_dominfo/__main__.py
textual_dominfo/dom_info.py
textual_dominfo/py.typed
textual_dominfo-0.1.0.dist-info/METADATA
textual_dominfo-0.1.0.dist-info/WHEEL
textual_dominfo-0.1.0.dist-info/top_level.txt
textual_dominfo-0.1.0.dist-info/RECORD
